fitdist/__init__.py
fitdist/examples.py
fitdist/fitdist.py
fitdist-0.2.0.dist-info/licenses/LICENSE
fitdist-0.2.0.dist-info/METADATA
fitdist-0.2.0.dist-info/WHEEL
fitdist-0.2.0.dist-info/top_level.txt
fitdist-0.2.0.dist-info/RECORD
