Metadata-Version: 2.4
Name: fitdist
Version: 0.2.0
Summary: fitdist is a Python package for probability density function fitting and hypothesis testing.
Author-email: Erdogan Taskesen <erdogant@gmail.com>
License: MIT License
Project-URL: Homepage, https://erdogant.github.io/distfit
Project-URL: Download, https://github.com/erdogant/fitdist/archive/{version}.tar.gz
Keywords: Python,
Classifier: Programming Language :: Python :: 3
Classifier: License :: OSI Approved :: MIT License
Classifier: Operating System :: OS Independent
Requires-Python: >=3
License-File: LICENSE
Requires-Dist: numpy
Requires-Dist: matplotlib>=3.5.2
Requires-Dist: tqdm
Requires-Dist: datazets
Requires-Dist: distfit
Dynamic: license-file
